grisly-0.0.4.dist-info/METADATA
grisly-0.0.4.dist-info/WHEEL
grisly-0.0.4.dist-info/license_files/LICENSE
grisly/_preprocessing.py
grisly/__init__.py
grisly/py.typed
grisly/grisly.cpython-312-darwin.so
grisly-0.0.4.dist-info/RECORD
