Metadata-Version: 2.1
Name: grisly
Version: 0.0.4
Classifier: Programming Language :: Python :: 3
Classifier: License :: OSI Approved :: MIT License
License-File: LICENSE
Summary: your_description_here
Author-email: Cangyuan Li <everest229@gmail.com>
Requires-Python: >=3.7
Project-URL: Homepage, https://github.com/CangyuanLi/grisly
Project-URL: Source, https://github.com/CangyuanLi/grisly
Project-URL: Bug Reports, https://github.com/CangyuanLi/grisly/issues
